markdown_toc-1.2.6.data/scripts/markdown-toc
markdowntoc/__init__.py
markdowntoc/markdowntoc.py
markdown_toc-1.2.6.dist-info/LICENSE
markdown_toc-1.2.6.dist-info/METADATA
markdown_toc-1.2.6.dist-info/WHEEL
markdown_toc-1.2.6.dist-info/top_level.txt
markdown_toc-1.2.6.dist-info/RECORD
