Metadata-Version: 2.1
Name: markdown-toc
Version: 1.2.6
Summary: Autogenerated Table of Contents for Github Markdown or Bear Notes
Home-page: https://github.com/alexander-lee/markdown-github-bear-toc
Author: Alexander Lee
Author-email: hello@alexanderlee.co
License: LICENSE
Keywords: markdown md github bear table of contents toc
Platform: UNKNOWN
Requires-Dist: python-dateutil
